GDynaDist/GDynaDist.py
GDynaDist/__init__.py
gdynadist-0.1.1.dist-info/licenses/LICENCE
gdynadist-0.1.1.dist-info/METADATA
gdynadist-0.1.1.dist-info/WHEEL
gdynadist-0.1.1.dist-info/top_level.txt
gdynadist-0.1.1.dist-info/RECORD
