Metadata-Version: 2.4
Name: GDynaDist
Version: 0.1.1
Summary: GDynaDist: an embedding-based distance for temporal graphs
Author: Lorenzo Dall`Amico, Ciro Cattuto, Alain Barrat
Author-email: "Lorenzo Dall'Amico, Ciro Cattuto, Alain Barrat" <lorenzo.dallamico@isi.it>
Requires-Python: >=3.9
License-File: LICENCE
Requires-Dist: edrep==0.1.2
Dynamic: license-file
